firebase_functions/__init__.py
firebase_functions/alerts_fn.py
firebase_functions/core.py
firebase_functions/db_fn.py
firebase_functions/eventarc_fn.py
firebase_functions/firestore_fn.py
firebase_functions/https_fn.py
firebase_functions/identity_fn.py
firebase_functions/logger.py
firebase_functions/options.py
firebase_functions/params.py
firebase_functions/pubsub_fn.py
firebase_functions/py.typed
firebase_functions/remote_config_fn.py
firebase_functions/scheduler_fn.py
firebase_functions/storage_fn.py
firebase_functions/tasks_fn.py
firebase_functions/test_lab_fn.py
firebase_functions/alerts/__init__.py
firebase_functions/alerts/app_distribution_fn.py
firebase_functions/alerts/billing_fn.py
firebase_functions/alerts/crashlytics_fn.py
firebase_functions/alerts/performance_fn.py
firebase_functions/private/__init__.py
firebase_functions/private/_alerts_fn.py
firebase_functions/private/_identity_fn.py
firebase_functions/private/manifest.py
firebase_functions/private/path_pattern.py
firebase_functions/private/serving.py
firebase_functions/private/token_verifier.py
firebase_functions/private/util.py
firebase_functions-0.4.3.dist-info/LICENSE
firebase_functions-0.4.3.dist-info/METADATA
firebase_functions-0.4.3.dist-info/WHEEL
firebase_functions-0.4.3.dist-info/top_level.txt
firebase_functions-0.4.3.dist-info/RECORD
